prayer_times_calculator/__init__.py
prayer_times_calculator/exceptions.py
prayer_times_calculator/pray_times_calculator.py
prayer_times_calculator-0.0.5.dist-info/LICENSE
prayer_times_calculator-0.0.5.dist-info/METADATA
prayer_times_calculator-0.0.5.dist-info/WHEEL
prayer_times_calculator-0.0.5.dist-info/top_level.txt
prayer_times_calculator-0.0.5.dist-info/RECORD
