Metadata-Version: 2.1
Name: prayer-times-calculator
Version: 0.0.5
Summary: Prayer Times Calculator
Home-page: https://github.com/uchagani/prayer-times-calculator
Author: Umair Chagani
Author-email: umair.chagani@gmail.com
License: MIT
Platform: UNKNOWN
Requires-Dist: requests
